setup.py
distributions/Binomialdistribution.py
distributions/Gaussiandistribution.py
distributions/Generaldistribution.py
distributions/__init__.py
distributions2020.egg-info/PKG-INFO
distributions2020.egg-info/SOURCES.txt
distributions2020.egg-info/dependency_links.txt
distributions2020.egg-info/not-zip-safe
distributions2020.egg-info/top_level.txt